examples/__init__.py
examples/load_all.py
examples/run-holistic.py
examples/datasets/__init__.py
examples/datasets/data_check.py
examples/datasets/dgs_types.py
examples/datasets/sign2mint.py
sign_language_datasets/__init__.py
sign_language_datasets/datasets/__init__.py
sign_language_datasets/datasets/config.py
sign_language_datasets/datasets/warning.py
sign_language_datasets/datasets/asl_citizen/__init__.py
sign_language_datasets/datasets/asl_citizen/asl_citizen.py
sign_language_datasets/datasets/asl_citizen/holistic.poseheader
sign_language_datasets/datasets/asl_lex/__init__.py
sign_language_datasets/datasets/asl_lex/asl_lex.py
sign_language_datasets/datasets/asl_lex/asl_lex_test.py
sign_language_datasets/datasets/asl_lex/checksums.tsv
sign_language_datasets/datasets/asl_lex/data-key.csv
sign_language_datasets/datasets/asl_signs/__init__.py
sign_language_datasets/datasets/asl_signs/asl_signs.py
sign_language_datasets/datasets/asl_signs/holistic.poseheader
sign_language_datasets/datasets/aslg_pc12/__init__.py
sign_language_datasets/datasets/aslg_pc12/aslg_pc12.py
sign_language_datasets/datasets/aslg_pc12/aslg_pc12_test.py
sign_language_datasets/datasets/aslg_pc12/checksums.tsv
sign_language_datasets/datasets/autsl/__init__.py
sign_language_datasets/datasets/autsl/autsl.py
sign_language_datasets/datasets/autsl/autsl_test.py
sign_language_datasets/datasets/autsl/checksums.tsv
sign_language_datasets/datasets/autsl/holistic.poseheader
sign_language_datasets/datasets/autsl/openpose_135.poseheader
sign_language_datasets/datasets/autsl/dummy_data/labels.csv
sign_language_datasets/datasets/bsl_corpus/__init__.py
sign_language_datasets/datasets/bsl_corpus/bsl_corpus.py
sign_language_datasets/datasets/bsl_corpus/bsl_corpus_test.py
sign_language_datasets/datasets/bsl_corpus/bsl_corpus_utils.py
sign_language_datasets/datasets/bsl_corpus/checksums.tsv
sign_language_datasets/datasets/chicago_fs_wild/__init__.py
sign_language_datasets/datasets/chicago_fs_wild/checksums.tsv
sign_language_datasets-0.3.0.dist-info/METADATA
sign_language_datasets-0.3.0.dist-info/WHEEL
sign_language_datasets-0.3.0.dist-info/top_level.txt
sign_language_datasets-0.3.0.dist-info/RECORD
