Metadata-Version: 2.4
Name: sign-language-datasets
Version: 0.3.0
Summary: TFDS Datasets for sign language
Author-email: Amit Moryossef <amitmoryossef@gmail.com>
Requires-Python: >=3.6
Requires-Dist: typing-extensions
Requires-Dist: python-dotenv
Requires-Dist: tqdm
Requires-Dist: pose-format>=0.0.3
Requires-Dist: tensorflow-datasets
Requires-Dist: numpy
Requires-Dist: Pillow
Requires-Dist: requests
Requires-Dist: etils
Requires-Dist: lxml
Requires-Dist: pympi-ling
Requires-Dist: tensorflow; platform_system != "Darwin"
Requires-Dist: tensorflow-macos; platform_system == "Darwin"
Provides-Extra: video
Requires-Dist: opencv-python; extra == "video"
Provides-Extra: dev
Requires-Dist: pylint; extra == "dev"
Requires-Dist: pytest; extra == "dev"
Requires-Dist: pytest-cov; extra == "dev"
Requires-Dist: black; extra == "dev"
